faster/__init__.py
faster/faster.py
faster/pip.json
faster-0.1.11.dist-info/DESCRIPTION.rst
faster-0.1.11.dist-info/METADATA
faster-0.1.11.dist-info/RECORD
faster-0.1.11.dist-info/WHEEL
faster-0.1.11.dist-info/entry_points.txt
faster-0.1.11.dist-info/metadata.json
faster-0.1.11.dist-info/top_level.txt
